storedisagg/__init__.py
storedisagg/compcalc.py
storedisagg/storagedisaggregator.py
storedisagg/example/__init__.py
storedisagg/example/example_data.py
storedisagg/example/std_example.py
storedisagg-1.0.1.dist-info/AUTHORS
storedisagg-1.0.1.dist-info/LICENSE
storedisagg-1.0.1.dist-info/METADATA
storedisagg-1.0.1.dist-info/WHEEL
storedisagg-1.0.1.dist-info/top_level.txt
storedisagg-1.0.1.dist-info/RECORD
